yaml/profiles/__init__.py
yaml/profiles/nested_dict_value.py
yaml/profiles/variables.py
yaml/profiles/yaml_parse.py
yamlprofiles/__init__.py
yamlprofiles/nested_dict_value.py
yamlprofiles/variables.py
yamlprofiles/yaml_parse.py
YamlProfiles-0.0.1.dist-info/LICENSE
YamlProfiles-0.0.1.dist-info/METADATA
YamlProfiles-0.0.1.dist-info/WHEEL
YamlProfiles-0.0.1.dist-info/top_level.txt
YamlProfiles-0.0.1.dist-info/RECORD
