Metadata-Version: 2.1
Name: YamlProfiles
Version: 0.0.1
Summary: UNKNOWN
Home-page: https://www.obatu.com
Author: liuyunfeng
Author-email: yunfound@outlook.com
License: UNKNOWN
Project-URL: Source Code, https://github.com/yunfong/yaml.profiles
Platform: UNKNOWN
Classifier: Programming Language :: Python :: 3
Classifier: License :: OSI Approved :: MIT License
Classifier: Operating System :: OS Independent
Requires-Python: >3.6
Requires-Dist: PyYAML (==5.4.1)
